MANIFEST.in
README.md
setup.cfg
setup.py
gae_env/__init__.py
gae_env/constants.py
gae_env/errors.py
gae_env/models.py
gae_env/utils.py
gae_env.egg-info/PKG-INFO
gae_env.egg-info/SOURCES.txt
gae_env.egg-info/dependency_links.txt
gae_env.egg-info/not-zip-safe
gae_env.egg-info/top_level.txt