Metadata-Version: 2.1
Name: gae-env
Version: 0.1.2
Summary: Google Appengine environment variables stored in Cloud Datastore (and/or system environment variables)
Home-page: https://github.com/Odame/gae-env
Author: Prince Odame
Author-email: opodame@gmail.com
License: MIT
Keywords: google appengine env var environment variable cloud datastore
Platform: UNKNOWN
Classifier: Development Status :: 4 - Beta
Classifier: License :: OSI Approved :: MIT License
Classifier: Programming Language :: Python :: 2.7
Classifier: Topic :: Software Development :: Libraries
